{
  "type": "minecraft:block",
  "pools": [
    {
      "rolls": 1,
      "entries": [
        {
          "type": "minecraft:item",
          "name": "cobblemon:green_apricorn",
          "conditions": [
            {
              "condition": "minecraft:block_state_property",
              "block": "cobblemon:green_apricorn",
              "properties": {
                "age": "3"
              }
            }
          ]
        }
      ]
    },
    {
      "rolls": 1,
      "entries": [
        {
          "type": "minecraft:item",
          "name": "cobblemon:green_apricorn_seed",
          "conditions": [
            {
              "condition": "minecraft:block_state_property",
              "block": "cobblemon:green_apricorn",
              "properties": {
                "age": "3"
              }
            },
            {
              "condition": "minecraft:random_chance",
              "chance": 0.1
            }
          ]
        }
      ]
    },
    {
      "rolls": 1,
      "entries": [
        {
          "type": "minecraft:item",
          "name": "pokeblocks:pokedoll_shiny_ivysaur",
          "conditions": [
            {
              "condition": "minecraft:block_state_property",
              "block": "cobblemon:white_apricorn",
              "properties": {
                "age": "3"
              }
            },
            {
              "condition": "minecraft:random_chance",
              "chance": 0.00011
            }
          ]
        }
      ]
    },
    {
      "rolls": 1,
      "entries": [
        {
          "type": "minecraft:item",
          "name": "pokeblocks:pokedoll_shiny_bulbasaur",
          "conditions": [
            {
              "condition": "minecraft:block_state_property",
              "block": "cobblemon:white_apricorn",
              "properties": {
                "age": "3"
              }
            },
            {
              "condition": "minecraft:random_chance",
              "chance": 0.00011
            }
          ]
        }
      ]
    },
    {
      "rolls": 1,
      "entries": [
        {
          "type": "minecraft:item",
          "name": "pokeblocks:pokedoll_shiny_venusaur",
          "conditions": [
            {
              "condition": "minecraft:block_state_property",
              "block": "cobblemon:white_apricorn",
              "properties": {
                "age": "3"
              }
            },
            {
              "condition": "minecraft:random_chance",
              "chance": 0.00011
            }
          ]
        }
      ]
    }
  ]
}
